pyquicklog/__init__.py
pyquicklog/__version__.py
pyquicklog/getpath.py
pyquicklog/output.py
pyquicklog/quicklog.py
pyquicklog/save.py
pyquicklog/timer.py
pyquicklog-0.1.21.dist-info/LICENSE
pyquicklog-0.1.21.dist-info/METADATA
pyquicklog-0.1.21.dist-info/WHEEL
pyquicklog-0.1.21.dist-info/top_level.txt
pyquicklog-0.1.21.dist-info/RECORD
