Metadata-Version: 2.1
Name: pyquicklog
Version: 0.1.21
Summary: A simple logger for python
Home-page: https://github.com/bbenouarets/pyquicklog
Author: Björn Benouarets
Author-email: contact@quickproject.tech
License: MIT license
Project-URL: Documentation, https://pyquicklog.quickproject.tech
Project-URL: Source, https://github.com/bbenouarets/pyquicklog
Project-URL: Download, https://github.com/bbenouarets/pyquicklog
License-File: LICENSE
